{
      "target": "cobblemon:bayleef",
      "features": ["rlm"],
      "forms": [
        {
            "name": "rlm",
            "aspects": [
              "rlm"
            ],
          "pokedex": [
            "cobblemon.species.bayleef-rlm.desc"
          ],
          "preEvolution": "chikorita",
        "evolutions": [
          {
            "id": "bayleef_meganium_rlm",
            "variant": "level_up",
            "result": "meganium rlm=true",
            "consumeHeldItem": false,
            "learnableMoves": [
              "spikyshield "
            ],
            "requirements": [
              {
                "variant": "level",
                "minLevel": 32
              }
            ]
          }
        ]
      }
    ]
  }