{
    "enabled": true,
    "neededInstalledMods": [],
    "neededUninstalledMods": [],
    "spawns": [
        {
            "id": "aphelis-1",
            "pokemon": "aphelis",
            "presets": [
                "natural"
            ],
            "timeRange": [
                "any"
            ],
            "type": "pokemon",
            "context": "grounded",
            "bucket": "rare",
            "level": "35-55",
            "weight": 5.0,
            "condition": {
                "canSeeSky": true,
                "biomes": [
                    "#cobblemon:is_mountain"
                ]
            }
        }
    ]
}